molvis/__init__.py
molvis/cli.py
molvis/core.py
molvis/utils.py
molvis/version.py
molvis-0.4.2.dist-info/LICENSE
molvis-0.4.2.dist-info/METADATA
molvis-0.4.2.dist-info/WHEEL
molvis-0.4.2.dist-info/entry_points.txt
molvis-0.4.2.dist-info/top_level.txt
molvis-0.4.2.dist-info/RECORD
